abdutils/__init__.py
abdutils/abdaugs.py
abdutils/abdutils.py
abdutils-0.0.2.dist-info/METADATA
abdutils-0.0.2.dist-info/WHEEL
abdutils-0.0.2.dist-info/top_level.txt
abdutils-0.0.2.dist-info/RECORD
