Metadata-Version: 2.1
Name: abdutils
Version: 0.0.2
Summary: A bag of utility functions.
Home-page: https://github.com/abdkhanstd/abdutils
Author: ABD
Author-email: abdkhan@163.com
License: MIT
Classifier: Programming Language :: Python :: 3
Classifier: License :: OSI Approved :: MIT License
Classifier: Operating System :: OS Independent
Requires-Python: >=3.6
Requires-Dist: Pillow
Requires-Dist: opencv-python
Requires-Dist: matplotlib
Requires-Dist: numpy
Requires-Dist: GPUtil
